daytona/__init__.py
daytona-1.0.1.dist-info/METADATA
daytona-1.0.1.dist-info/WHEEL
daytona-1.0.1.dist-info/top_level.txt
daytona-1.0.1.dist-info/RECORD
