Metadata-Version: 2.4
Name: daytona
Version: 1.0.1
Summary: Shim package that installs daytona-sdk
Author-email: Daytona <support@daytona.io>
License-Expression: AGPL-3.0
Requires-Python: >=3.7
Requires-Dist: daytona-sdk
